pyvvisf/__init__.py
pyvvisf/_version.py
pyvvisf/errors.py
pyvvisf/framebuffer_manager.py
pyvvisf/input_manager.py
pyvvisf/parser.py
pyvvisf/renderer.py
pyvvisf/shader_compiler.py
pyvvisf/types.py
pyvvisf-0.7.1.dist-info/licenses/LICENSE
pyvvisf-0.7.1.dist-info/METADATA
pyvvisf-0.7.1.dist-info/WHEEL
pyvvisf-0.7.1.dist-info/top_level.txt
pyvvisf-0.7.1.dist-info/RECORD
