Metadata-Version: 2.4
Name: pyvvisf
Version: 0.7.1
Summary: Pure Python ISF shader renderer with PyOpenGL and json5
Author-email: Jim Cortez <gitstuff@jimcortez.com>
License: MIT License
Project-URL: Homepage, https://github.com/jimcortez/pyvvisf
Project-URL: Repository, https://github.com/jimcortez/pyvvisf
Project-URL: Documentation, https://github.com/jimcortez/pyvvisf#readme
Project-URL: Issues, https://github.com/jimcortez/pyvvisf/issues
Classifier: Development Status :: 4 - Beta
Classifier: Intended Audience :: Developers
Classifier: Programming Language :: Python :: 3
Classifier: Programming Language :: Python :: 3.8
Classifier: Programming Language :: Python :: 3.9
Classifier: Programming Language :: Python :: 3.10
Classifier: Programming Language :: Python :: 3.11
Classifier: Programming Language :: Python :: 3.12
Classifier: Topic :: Multimedia :: Graphics
Classifier: Topic :: Scientific/Engineering :: Image Processing
Classifier: Topic :: Software Development :: Libraries :: Python Modules
Classifier: Operating System :: OS Independent
Requires-Python: >=3.8
License-File: LICENSE
Requires-Dist: glfw>=2.5.0
Requires-Dist: PyOpenGL>=3.1.0
Requires-Dist: PyOpenGL-accelerate>=3.1.0
Requires-Dist: json5>=0.9.0
Requires-Dist: pillow>=9.0.0
Requires-Dist: numpy>=1.21.0
Requires-Dist: pydantic>=1.8.0
Provides-Extra: dev
Requires-Dist: pytest>=7.0.0; extra == "dev"
Requires-Dist: pytest-cov>=4.0.0; extra == "dev"
Requires-Dist: black>=22.0.0; extra == "dev"
Requires-Dist: isort>=5.0.0; extra == "dev"
Requires-Dist: flake8>=5.0.0; extra == "dev"
Requires-Dist: mypy>=1.0.0; extra == "dev"
Requires-Dist: pre-commit>=2.20.0; extra == "dev"
Requires-Dist: cibuildwheel>=3.0.0; extra == "dev"
Requires-Dist: build>=0.10.0; extra == "dev"
Dynamic: license-file
